imutesting/__init__.py
imutesting/filters/EKF.py
imutesting/filters/Extend_Kalman_Filter.py
imutesting/filters/__init__.py
imutesting/math/Quaternion.py
imutesting/math/__init__.py
imutesting-0.0.20.dist-info/LICENSE.txt
imutesting-0.0.20.dist-info/METADATA
imutesting-0.0.20.dist-info/WHEEL
imutesting-0.0.20.dist-info/top_level.txt
imutesting-0.0.20.dist-info/RECORD
