Metadata-Version: 2.1
Name: imutesting
Version: 0.0.20
Summary: This package provides an Extended Kalman Filter (EKF) algorithm for attitude estimation by fusing data from inertial measurement unit (IMU) sensors. It offers robust and accurate estimation of Quaternion and Euler angles representing the orientation of the sensor in 3D space.
Author-email: zstary <zjt360424@gmail.com>
Classifier: Programming Language :: Python :: 3
Classifier: License :: OSI Approved :: MIT License
Classifier: Operating System :: OS Independent
Requires-Python: >=3.6
License-File: LICENSE.txt
